geoipset_proxmox/__init__.py
geoipset_proxmox/config.py
geoipset_proxmox/dbip.py
geoipset_proxmox/proxmox.py
geoipset_proxmox/static.py
geoipset_proxmox-0.0.0.dist-info/METADATA
geoipset_proxmox-0.0.0.dist-info/WHEEL
geoipset_proxmox-0.0.0.dist-info/entry_points.txt
geoipset_proxmox-0.0.0.dist-info/RECORD
