Metadata-Version: 2.4
Name: geoipset-proxmox
Version: 0.0.0
Summary: This project populates the Proxmox VE firewall ipset with GeoIP data to block or allow traffic based on geographic location.
Requires-Python: >=3.12
Requires-Dist: click>=8.2.1
Requires-Dist: proxmoxer>=2.2.0
Requires-Dist: requests>=2.32.4
Requires-Dist: rich>=14.0.0
